iprcssngpy/__init__.py
iprcssngpy/processing/__init__.py
iprcssngpy/processing/combination.py
iprcssngpy/processing/transformation.py
iprcssngpy/utils/__init__.py
iprcssngpy/utils/io.py
iprcssngpy/utils/plot.py
iprcssngpy-0.0.2.dist-info/METADATA
iprcssngpy-0.0.2.dist-info/WHEEL
iprcssngpy-0.0.2.dist-info/top_level.txt
iprcssngpy-0.0.2.dist-info/RECORD
