Metadata-Version: 2.1
Name: iprcssngpy
Version: 0.0.2
Summary: Package creation and image processing study
Author: Romário Pereira Marinho
Author-email: eng.romariopmarinho@gmail.com
Requires-Python: >=3.10
Requires-Dist: numpy (~=1.23.1)
Requires-Dist: scikit-image (~=0.19.2)
Requires-Dist: matplotlib (~=3.5.2)
